txt2tei/__init__.py
txt2tei/addmetre.py
txt2tei/authors.xml
txt2tei/edition.py
txt2tei/libtxt2tei.py
txt2tei/makelist.py
txt2tei/sexos.csv
txt2tei/tei2txt.py
txt2tei/txt2tei-a.py
txt2tei/txt2tei.py
txt2tei-1.0.7.dist-info/LICENSE
txt2tei-1.0.7.dist-info/METADATA
txt2tei-1.0.7.dist-info/WHEEL
txt2tei-1.0.7.dist-info/entry_points.txt
txt2tei-1.0.7.dist-info/top_level.txt
txt2tei-1.0.7.dist-info/RECORD
