Metadata-Version: 2.1
Name: txt2tei
Version: 1.0.7
Summary: An aid to encoding plays as XML-TEI
Home-page: https://github.com/fsanzl/txt2tei
Author: Fernando Sanz-Lázaro
Author-email: fsanzl@gmail.com
License: LGPL
Project-URL: Source, https://github.com/fsanzl/txt2tei/
Project-URL: Tracker, https://github.com/fsanzl/txt2tei/issues
Classifier: License :: OSI Approved :: GNU Lesser General Public License v2 or later (LGPLv2+)
Classifier: Programming Language :: Python :: 3
Classifier: Programming Language :: Python :: 3.9
Classifier: Programming Language :: Python :: 3.8
Classifier: Programming Language :: Python :: 3.7
Classifier: Programming Language :: Python :: 3.6
Classifier: Programming Language :: Python :: 3.5
Classifier: Natural Language :: Spanish
Requires-Python: >=3.5
License-File: LICENSE
Requires-Dist: chardet
Requires-Dist: datetime
Requires-Dist: lxml
Requires-Dist: pandas
Requires-Dist: unidecode
